{
  "_class": "shapePath",
  "booleanOperation": -1,
  "clippingMaskMode": 0,
  "do_objectID": "A670F99D-8E3F-4ADF-AD38-7595609AF04B",
  "edited": true,
  "exportOptions": {
    "_class": "exportOptions",
    "do_objectID": "BC996C88-014F-4E96-93D0-697BE284D72D",
    "exportFormats": [
    ],
    "includedLayerIds": [
    ],
    "layerOptions": 0,
    "shouldTrim": false
  },
  "frame": {
    "_class": "rect",
    "constrainProportions": false,
    "do_objectID": "F63FB20F-1EAE-462F-8BCA-BE5E28D0449C",
    "height": 39.21260000000001,
    "width": 29.5036,
    "x": 20.1866,
    "y": 10.92139999999999
  },
  "hasClippingMask": false,
  "isClosed": true,
  "isFixedToViewport": false,
  "isFlippedHorizontal": false,
  "isFlippedVertical": false,
  "isLocked": false,
  "isVisible": true,
  "layerListExpandedType": 0,
  "name": "路径",
  "nameIsFixed": false,
  "pointRadiusBehaviour": 1,
  "points": [
    {
      "_class": "curvePoint",
      "cornerRadius": 0,
      "curveFrom": "{0.68344879946853954, 0.62294262558463354}",
      "curveMode": 1,
      "curveTo": "{0.68344879946853954, 0.62294262558463354}",
      "hasCurveFrom": false,
      "hasCurveTo": false,
      "point": "{0.68344879946853954, 0.62294262558463354}"
    },
    {
      "_class": "curvePoint",
      "cornerRadius": 0,
      "curveFrom": "{0.68344879946853954, 0.83133992645221166}",
      "curveMode": 4,
      "curveTo": "{0.68344879946853954, 0.62408511549858969}",
      "hasCurveFrom": true,
      "hasCurveTo": false,
      "point": "{0.68344879946853954, 0.62408511549858969}"
    },
    {
      "_class": "curvePoint",
      "cornerRadius": 0,
      "curveFrom": "{0.11919901300180301, 1}",
      "curveMode": 3,
      "curveTo": "{0.45942867988991165, 1}",
      "hasCurveFrom": true,
      "hasCurveTo": true,
      "point": "{0.1846350953781912, 1}"
    },
    {
      "_class": "curvePoint",
      "cornerRadius": 0,
      "curveFrom": "{0, 0.97329429826127301}",
      "curveMode": 4,
      "curveTo": "{0.05684729999050965, 0.99050305259023863}",
      "hasCurveFrom": false,
      "hasCurveTo": true,
      "point": "{0, 0.97329429826127301}"
    },
    {
      "_class": "curvePoint",
      "cornerRadius": 0,
      "curveFrom": "{0.18397076966878612, 0.66985611767646114}",
      "curveMode": 4,
      "curveTo": "{0, 0.72508836445428237}",
      "hasCurveFrom": true,
      "hasCurveTo": false,
      "point": "{0, 0.72508836445428237}"
    },
    {
      "_class": "curvePoint",
      "cornerRadius": 0,
      "curveFrom": "{0.31493783809433407, 0.37587918169159912}",
      "curveMode": 4,
      "curveTo": "{0.31493783809433407, 0.53386411510585885}",
      "hasCurveFrom": false,
      "hasCurveTo": true,
      "point": "{0.31493783809433407, 0.37587918169159912}"
    },
    {
      "_class": "curvePoint",
      "cornerRadius": 0,
      "curveFrom": "{0.31579197114928331, 0.16862437073797712}",
      "curveMode": 4,
      "curveTo": "{0.31493783809433407, 0.37470098896783183}",
      "hasCurveFrom": true,
      "hasCurveTo": false,
      "point": "{0.31493783809433407, 0.37470098896783183}"
    },
    {
      "_class": "curvePoint",
      "cornerRadius": 0,
      "curveFrom": "{0.87999430577963356, 0}",
      "curveMode": 3,
      "curveTo": "{0.53985954256429713, 0}",
      "hasCurveFrom": true,
      "hasCurveTo": true,
      "point": "{0.81451077156685936, 0}"
    },
    {
      "_class": "curvePoint",
      "cornerRadius": 0,
      "curveFrom": "{1, 0.027348352315327399}",
      "curveMode": 4,
      "curveTo": "{0.94239347062731305, 0.0094969474097613363}",
      "hasCurveFrom": false,
      "hasCurveTo": true,
      "point": "{1, 0.027348352315327399}"
    },
    {
      "_class": "curvePoint",
      "cornerRadius": 0,
      "curveFrom": "{0.81531745278542267, 0.33014388232353875}",
      "curveMode": 4,
      "curveTo": "{1, 0.27491163554571746}",
      "hasCurveFrom": true,
      "hasCurveTo": false,
      "point": "{1, 0.27491163554571746}"
    },
    {
      "_class": "curvePoint",
      "cornerRadius": 0,
      "curveFrom": "{0.68435038435987472, 0.62294262558463354}",
      "curveMode": 4,
      "curveTo": "{0.68435038435987472, 0.46552893712735183}",
      "hasCurveFrom": false,
      "hasCurveTo": true,
      "point": "{0.68435038435987472, 0.62294262558463354}"
    }
  ],
  "resizingConstraint": 63,
  "resizingType": 0,
  "rotation": 0,
  "shouldBreakMaskChain": false,
  "style": {
    "_class": "style",
    "do_objectID": "361E4918-4DF6-4924-9718-B2B90168E9C3",
    "endMarkerType": 0,
    "miterLimit": 10,
    "startMarkerType": 0,
    "windingRule": 1
  }
}